{"id": 181, "name": {"english": "Ampharos", "japanese": "\u30c7\u30f3\u30ea\u30e5\u30a6", "chinese": "\u7535\u9f99"}, "type": ["Electric"], "base": {"HP": 90, "Attack": 75, "Defense": 85, "Sp. Attack": 115, "Sp. Defense": 90, "Speed": 55}, "species": "Light Pok\u00e9mon", "description": "The tip of its tail shines so brightly it can be used to send sea-navigation beacons to distant foreign shores.", "profile": {"Height": "1.4 m", "Weight": "61.5 kg", "Catch Rate": "0%", "Gender Ratio": "50% \u2642 50% \u2640", "Egg Groups": "Monster, Field", "Hatch Steps": "5100", "Abilities": "Static, Plus", "EVs": "3 Sp Att"}, "color": "246, 201, 19"}