{"id": 223, "name": {"english": "Remoraid", "japanese": "\u30c6\u30c3\u30dd\u30a6\u30aa", "chinese": "\u94c1\u70ae\u9c7c"}, "type": ["Water"], "base": {"HP": 35, "Attack": 65, "Defense": 35, "Sp. Attack": 65, "Sp. Defense": 35, "Speed": 65}, "species": "Jet Pok\u00e9mon", "description": "The water they shoot from their mouths can hit moving prey from more than 300 feet away.", "profile": {"Height": "0.6 m", "Weight": "12 kg", "Catch Rate": "0%", "Gender Ratio": "50% \u2642 50% \u2640", "Egg Groups": "Water 1, Water 2", "Hatch Steps": "5100", "Abilities": "Hustle, Sniper, Moody", "EVs": "1 Sp Att"}, "color": "69, 120, 237"}