{"name": {"english": "Latias", "japanese": "\u30e9\u30c6\u30a3\u30a2\u30b9", "chinese": "\u62c9\u5e1d\u4e9a\u65af"}, "type": ["Dragon", "Psychic"], "base": {"HP": 80, "Attack": 80, "Defense": 90, "Speed": 110, "SpAttack": 110, "SpDefense": 130}, "species": "Infinity Pok\u00e9mon", "description": "Its body is covered with a down that can refract light in such a way that it becomes invisible.", "profile": {"Height": "1.4 m", "Weight": "40 kg", "Abilities": "Levitate", "EVs": "3 Sp Def", "CatchRate": "0%", "GenderRatio": "0% \u2642 100% \u2640", "EggGroups": "No Eggs", "HatchSteps": "30600"}, "color": "247, 54, 112"}