{"id": 585, "name": {"english": "Deerling", "japanese": "\u30b7\u30ad\u30b8\u30ab", "chinese": "\u56db\u5b63\u9e7f"}, "type": ["Normal", "Grass"], "base": {"HP": 60, "Attack": 60, "Defense": 50, "Sp. Attack": 40, "Sp. Defense": 50, "Speed": 75}, "species": "Seasonal Pok\u00e9mon", "description": "Their coloring changes according to the seasons and can be slightly affected by the temperature and humidity as well.", "profile": {"Height": "0.6 m", "Weight": "19.5 kg", "Catch Rate": "0%", "Gender Ratio": "50% \u2642 50% \u2640", "Egg Groups": "Field", "Hatch Steps": "5100", "Abilities": "Serene-grace, Chlorophyll, Sap-sipper", "EVs": "1 Speed"}, "color": "105, 194, 61"}