{"id": 640, "name": {"english": "Virizion", "japanese": "\u30d3\u30ea\u30b8\u30aa\u30f3", "chinese": "\u6bd5\u529b\u5409\u7fc1"}, "type": ["Grass", "Fighting"], "base": {"HP": 91, "Attack": 90, "Defense": 72, "Sp. Attack": 90, "Sp. Defense": 129, "Speed": 108}, "species": "Grassland Pok\u00e9mon", "description": "Legends say this Pok\u00e9mon confounded opponents with its swift movements.", "profile": {"Height": "2 m", "Weight": "200 kg", "Catch Rate": "0%", "Gender Ratio": "N/A", "Egg Groups": "No Eggs", "Hatch Steps": "20400", "Abilities": "Justified", "EVs": "3 Sp Def"}, "color": "105, 194, 61"}