{"name": {"english": "Araquanid", "japanese": "\u30aa\u30cb\u30b7\u30ba\u30af\u30e2", "chinese": "\u6ef4\u86db\u9738"}, "type": ["Water", "Bug"], "base": {"HP": 68, "Attack": 70, "Defense": 92, "Speed": 42, "SpAttack": 50, "SpDefense": 132}, "species": "Paleozoic Pok\u00e9mon", "description": "This Pok\u00e9mon existed 300 million years ago. Team Plasma altered it and attached a cannon to its back.", "profile": {"Height": "1.5 m", "Weight": "82.5 kg", "Abilities": "Download", "EVs": "1 Attack, 1 Speed, 1 Sp Att", "CatchRate": "0%", "GenderRatio": "N/A", "EggGroups": "No Eggs", "HatchSteps": "30600"}, "color": "160, 160, 192"}