{"id": 777, "name": {"english": "Togedemaru", "japanese": "\u30c8\u30b2\u30c7\u30de\u30eb", "chinese": "\u6258\u6208\u5fb7\u739b\u5c14"}, "type": ["Electric", "Steel"], "base": {"HP": 65, "Attack": 98, "Defense": 63, "Sp. Attack": 40, "Sp. Defense": 73, "Speed": 96}, "species": "Paleozoic Pok\u00e9mon", "description": "This Pok\u00e9mon existed 300 million years ago. Team Plasma altered it and attached a cannon to its back.", "profile": {"Height": "1.5 m", "Weight": "82.5 kg", "Catch Rate": "0%", "Gender Ratio": "N/A", "Egg Groups": "No Eggs", "Hatch Steps": "30600", "Abilities": "Download", "EVs": "1 Attack, 1 Speed, 1 Sp Att"}, "color": "160, 160, 192"}