{"name": {"english": "Cosmog", "japanese": "\u30b3\u30b9\u30e2\u30c3\u30b0", "chinese": "\u79d1\u65af\u83ab\u53e4"}, "type": ["Psychic"], "base": {"HP": 43, "Attack": 29, "Defense": 31, "Speed": 37, "SpAttack": 29, "SpDefense": 31}, "species": "Paleozoic Pok\u00e9mon", "description": "This Pok\u00e9mon existed 300 million years ago. Team Plasma altered it and attached a cannon to its back.", "profile": {"Height": "1.5 m", "Weight": "82.5 kg", "Abilities": "Download", "EVs": "1 Attack, 1 Speed, 1 Sp Att", "CatchRate": "0%", "GenderRatio": "N/A", "EggGroups": "No Eggs", "HatchSteps": "30600"}, "color": "160, 160, 192"}