{"id": 800, "name": {"english": "Necrozma", "japanese": "\u30cd\u30af\u30ed\u30ba\u30de", "chinese": "\u5948\u514b\u6d1b\u5179\u739b"}, "type": ["Psychic"], "base": {"HP": 97, "Attack": 107, "Defense": 101, "Sp. Attack": 127, "Sp. Defense": 89, "Speed": 79}, "species": "Paleozoic Pok\u00e9mon", "description": "This Pok\u00e9mon existed 300 million years ago. Team Plasma altered it and attached a cannon to its back.", "profile": {"Height": "1.5 m", "Weight": "82.5 kg", "Catch Rate": "0%", "Gender Ratio": "N/A", "Egg Groups": "No Eggs", "Hatch Steps": "30600", "Abilities": "Download", "EVs": "1 Attack, 1 Speed, 1 Sp Att"}, "color": "160, 160, 192"}