{"id": 401, "moves": {"learn": [{"lv": "1", "name": "Bide", "type": "Normal", "cat": "Physical", "power": "\u2014", "acc": "\u2014"}, {"lv": "1", "name": "Growl", "type": "Normal", "cat": "Status", "power": "\u2014", "acc": "100"}, {"lv": "6", "name": "Struggle Bug", "type": "Bug", "cat": "Special", "power": "50", "acc": "100"}, {"lv": "16", "name": "Bug Bite", "type": "Bug", "cat": "Physical", "power": "60", "acc": "100"}], "egg": [{"name": "Bug Bite", "type": "Bug", "cat": "Physical", "power": "60", "acc": "100"}, {"name": "Endeavor", "type": "Normal", "cat": "Physical", "power": "\u2014", "acc": "100"}, {"name": "Snore", "type": "Normal", "cat": "Special", "power": "50", "acc": "100"}, {"name": "Uproar", "type": "Normal", "cat": "Special", "power": "90", "acc": "100"}], "tm": [], "tutor": [{"name": "Bug Bite", "type": "Bug", "cat": "Physical", "power": "60", "acc": "100"}, {"name": "Endeavor", "type": "Normal", "cat": "Physical", "power": "\u2014", "acc": "100"}, {"name": "Snore", "type": "Normal", "cat": "Special", "power": "50", "acc": "100"}, {"name": "Uproar", "type": "Normal", "cat": "Special", "power": "90", "acc": "100"}], "transfer": [{"name": "Mud-Slap", "type": "Ground", "cat": "Special", "power": "20", "acc": "100"}, {"name": "String Shot", "type": "Bug", "cat": "Status", "power": "\u2014", "acc": "95"}]}}